django_rest_github_oauth/__init__.py
django_rest_github_oauth/admin.py
django_rest_github_oauth/apps.py
django_rest_github_oauth/github.py
django_rest_github_oauth/models.py
django_rest_github_oauth/register.py
django_rest_github_oauth/response.py
django_rest_github_oauth/settings.py
django_rest_github_oauth/signals.py
django_rest_github_oauth/urls.py
django_rest_github_oauth/utils.py
django_rest_github_oauth/views.py
django_rest_github_oauth/migrations/0001_initial.py
django_rest_github_oauth/migrations/__init__.py
django_rest_github_oauth-0.1.2.dist-info/AUTHORS.rst
django_rest_github_oauth-0.1.2.dist-info/LICENSE
django_rest_github_oauth-0.1.2.dist-info/METADATA
django_rest_github_oauth-0.1.2.dist-info/WHEEL
django_rest_github_oauth-0.1.2.dist-info/top_level.txt
django_rest_github_oauth-0.1.2.dist-info/RECORD
