Metadata-Version: 2.1
Name: django-rest-github-oauth
Version: 0.1.2
Summary: A simple python library to authenticate users with github in Django applications.
Home-page: https://github.com/mabdullahadeel/django-rest-github-oauth
Author: Abdullah Adeel
Author-email: business.info.abd@gmail.com
License: MIT license
Keywords: django_rest_github_oauth,django,github,oauth,rest,restframework
Platform: UNKNOWN
Classifier: Development Status :: 2 - Pre-Alpha
Classifier: Intended Audience :: Developers
Classifier: License :: OSI Approved :: MIT License
Classifier: Natural Language :: English
Classifier: Programming Language :: Python :: 3
Classifier: Programming Language :: Python :: 3.6
Classifier: Programming Language :: Python :: 3.7
Classifier: Programming Language :: Python :: 3.8
Classifier: Programming Language :: Python :: 3.9
Classifier: Framework :: Django
Classifier: Framework :: Django :: 2.0
Classifier: Framework :: Django :: 2.1
Classifier: Framework :: Django :: 2.2
Classifier: Framework :: Django :: 3.0
Classifier: Framework :: Django :: 3.1
Classifier: Framework :: Django :: 3.2
Classifier: Framework :: Django :: 4.0
Requires-Python: >=3.7
License-File: LICENSE
License-File: AUTHORS.rst
Requires-Dist: Django (>=2.0)
Requires-Dist: djangorestframework (>=3.0)
Requires-Dist: requests (>=2.0)
